ubootenv/__init__.py
ubootenv-0.1.1.dist-info/licenses/LICENSE
ubootenv-0.1.1.dist-info/METADATA
ubootenv-0.1.1.dist-info/WHEEL
ubootenv-0.1.1.dist-info/top_level.txt
ubootenv-0.1.1.dist-info/RECORD
