Metadata-Version: 2.4
Name: ubootenv
Version: 0.1.1
Summary: U-Boot environment setter and getter from the C library libubootenv
Author-email: Pierre-Loup GOSSE <pierreloupgosse@gmail.com>
Project-URL: Homepage, https://gitlab.com/PierreLoupG/ubootenv
Project-URL: Issues, https://gitlab.com/PierreLoupG/ubootenv/issues
Classifier: Programming Language :: Python :: 3
Classifier: Operating System :: OS Independent
Requires-Python: >=3.9
License-File: LICENSE
Dynamic: license-file
